marqtune/__init__.py
marqtune/client.py
marqtune/config.py
marqtune/enums.py
marqtune/httprequests.py
marqtune-0.2.7.dist-info/METADATA
marqtune-0.2.7.dist-info/WHEEL
marqtune-0.2.7.dist-info/top_level.txt
marqtune-0.2.7.dist-info/RECORD
