Metadata-Version: 2.2
Name: marqtune
Version: 0.2.7
Summary: Client for marqtune
Author: marqo org
Author-email: org@marqo.io
Keywords: search python marqo opensearch tensor neural semantic vector embedding
Classifier: Programming Language :: Python :: 3.9
Classifier: License :: OSI Approved :: Apache Software License
Classifier: Operating System :: OS Independent
Requires-Python: >=3
Requires-Dist: requests
Requires-Dist: urllib3
Dynamic: author
Dynamic: author-email
Dynamic: classifier
Dynamic: description
Dynamic: description-content-type
Dynamic: keywords
Dynamic: requires-dist
Dynamic: requires-python
Dynamic: summary
